[
  {
    "availability": "available",
    "currency": "USD",
    "expiresAt": "2026-07-24T11:10:41.000Z",
    "fulfillmentModes": [
      "pickup",
      "delivery",
      "in-store"
    ],
    "id": "kroger-observation-53100516-0001111001129-2026-07-24",
    "itemSize": "1 gal",
    "limitation": "Dated internal research observation for one governed Mariano’s location; public live price comparison remains disabled.",
    "locationId": "kroger-location-53100516",
    "mappingId": "kroger-0001111001129",
    "observedAt": "2026-07-24T05:10:41Z",
    "priceAmount": 8.49,
    "priceType": "regular",
    "promotionalPrice": null,
    "providerInventoryState": "LOW",
    "publicationState": "internal-only",
    "regularPrice": 8.49,
    "sourceId": "kroger"
  },
  {
    "availability": "available",
    "currency": "USD",
    "expiresAt": "2026-07-24T11:10:41.000Z",
    "fulfillmentModes": [
      "pickup",
      "delivery",
      "in-store"
    ],
    "id": "kroger-observation-53100516-0001111004807-2026-07-24",
    "itemSize": "26 oz",
    "limitation": "Dated internal research observation for one governed Mariano’s location; public live price comparison remains disabled.",
    "locationId": "kroger-location-53100516",
    "mappingId": "kroger-0001111004807",
    "observedAt": "2026-07-24T05:10:41Z",
    "priceAmount": 1.79,
    "priceType": "regular",
    "promotionalPrice": null,
    "providerInventoryState": "HIGH",
    "publicationState": "internal-only",
    "regularPrice": 1.79,
    "sourceId": "kroger"
  },
  {
    "availability": "available",
    "currency": "USD",
    "expiresAt": "2026-07-24T11:10:41.000Z",
    "fulfillmentModes": [
      "pickup",
      "delivery",
      "in-store"
    ],
    "id": "kroger-observation-53100516-0001111004808-2026-07-24",
    "itemSize": "26 oz",
    "limitation": "Dated internal research observation for one governed Mariano’s location; public live price comparison remains disabled.",
    "locationId": "kroger-location-53100516",
    "mappingId": "kroger-0001111004808",
    "observedAt": "2026-07-24T05:10:41Z",
    "priceAmount": 1.79,
    "priceType": "regular",
    "promotionalPrice": null,
    "providerInventoryState": "HIGH",
    "publicationState": "internal-only",
    "regularPrice": 1.79,
    "sourceId": "kroger"
  },
  {
    "availability": "available",
    "currency": "USD",
    "expiresAt": "2026-07-24T11:10:41.000Z",
    "fulfillmentModes": [
      "pickup",
      "delivery",
      "in-store"
    ],
    "id": "kroger-observation-53100516-0001111011888-2026-07-24",
    "itemSize": "4 lb",
    "limitation": "Dated internal research observation for one governed Mariano’s location; public live price comparison remains disabled.",
    "locationId": "kroger-location-53100516",
    "mappingId": "kroger-0001111011888",
    "observedAt": "2026-07-24T05:10:41Z",
    "priceAmount": 3.29,
    "priceType": "regular",
    "promotionalPrice": null,
    "providerInventoryState": "HIGH",
    "publicationState": "internal-only",
    "regularPrice": 3.29,
    "sourceId": "kroger"
  },
  {
    "availability": "available",
    "currency": "USD",
    "expiresAt": "2026-07-24T11:10:41.000Z",
    "fulfillmentModes": [
      "pickup",
      "delivery",
      "in-store"
    ],
    "id": "kroger-observation-53100516-0001111011889-2026-07-24",
    "itemSize": "10 lbs",
    "limitation": "Dated internal research observation for one governed Mariano’s location; public live price comparison remains disabled.",
    "locationId": "kroger-location-53100516",
    "mappingId": "kroger-0001111011889",
    "observedAt": "2026-07-24T05:10:41Z",
    "priceAmount": 7.29,
    "priceType": "regular",
    "promotionalPrice": null,
    "providerInventoryState": "HIGH",
    "publicationState": "internal-only",
    "regularPrice": 7.29,
    "sourceId": "kroger"
  },
  {
    "availability": "available",
    "currency": "USD",
    "expiresAt": "2026-07-24T11:10:41.000Z",
    "fulfillmentModes": [
      "pickup",
      "delivery",
      "in-store"
    ],
    "id": "kroger-observation-53100516-0001111072567-2026-07-24",
    "itemSize": "15.25 oz",
    "limitation": "Dated internal research observation for one governed Mariano’s location; public live price comparison remains disabled.",
    "locationId": "kroger-location-53100516",
    "mappingId": "kroger-0001111072567",
    "observedAt": "2026-07-24T05:10:41Z",
    "priceAmount": 1.59,
    "priceType": "regular",
    "promotionalPrice": null,
    "providerInventoryState": "HIGH",
    "publicationState": "internal-only",
    "regularPrice": 1.59,
    "sourceId": "kroger"
  },
  {
    "availability": "available",
    "currency": "USD",
    "expiresAt": "2026-07-24T11:10:41.000Z",
    "fulfillmentModes": [
      "pickup",
      "delivery",
      "in-store"
    ],
    "id": "kroger-observation-53100516-0001111085004-2026-07-24",
    "itemSize": "16 oz",
    "limitation": "Dated internal research observation for one governed Mariano’s location; public live price comparison remains disabled.",
    "locationId": "kroger-location-53100516",
    "mappingId": "kroger-0001111085004",
    "observedAt": "2026-07-24T05:10:41Z",
    "priceAmount": 1.79,
    "priceType": "regular",
    "promotionalPrice": null,
    "providerInventoryState": "HIGH",
    "publicationState": "internal-only",
    "regularPrice": 1.79,
    "sourceId": "kroger"
  },
  {
    "availability": "available",
    "currency": "USD",
    "expiresAt": "2026-07-24T11:10:41.000Z",
    "fulfillmentModes": [
      "pickup",
      "delivery",
      "in-store"
    ],
    "id": "kroger-observation-53100516-0001111085402-2026-07-24",
    "itemSize": "5 lb",
    "limitation": "Dated internal research observation for one governed Mariano’s location; public live price comparison remains disabled.",
    "locationId": "kroger-location-53100516",
    "mappingId": "kroger-0001111085402",
    "observedAt": "2026-07-24T05:10:41Z",
    "priceAmount": 3.79,
    "priceType": "regular",
    "promotionalPrice": null,
    "providerInventoryState": "HIGH",
    "publicationState": "internal-only",
    "regularPrice": 3.79,
    "sourceId": "kroger"
  },
  {
    "availability": "available",
    "currency": "USD",
    "expiresAt": "2026-07-24T11:10:41.000Z",
    "fulfillmentModes": [
      "pickup",
      "delivery",
      "in-store"
    ],
    "id": "kroger-observation-53100516-0001111085451-2026-07-24",
    "itemSize": "16 oz",
    "limitation": "Dated internal research observation for one governed Mariano’s location; public live price comparison remains disabled.",
    "locationId": "kroger-location-53100516",
    "mappingId": "kroger-0001111085451",
    "observedAt": "2026-07-24T05:10:41Z",
    "priceAmount": 1.09,
    "priceType": "regular",
    "promotionalPrice": null,
    "providerInventoryState": "HIGH",
    "publicationState": "internal-only",
    "regularPrice": 1.09,
    "sourceId": "kroger"
  },
  {
    "availability": "available",
    "currency": "USD",
    "expiresAt": "2026-07-24T11:10:41.000Z",
    "fulfillmentModes": [
      "pickup",
      "delivery",
      "in-store"
    ],
    "id": "kroger-observation-53100516-0001111086116-2026-07-24",
    "itemSize": "5 lb",
    "limitation": "Dated internal research observation for one governed Mariano’s location; public live price comparison remains disabled.",
    "locationId": "kroger-location-53100516",
    "mappingId": "kroger-0001111086116",
    "observedAt": "2026-07-24T05:10:41Z",
    "priceAmount": 3.79,
    "priceType": "regular",
    "promotionalPrice": null,
    "providerInventoryState": "LOW",
    "publicationState": "internal-only",
    "regularPrice": 3.79,
    "sourceId": "kroger"
  },
  {
    "availability": "available",
    "currency": "USD",
    "expiresAt": "2026-07-24T11:10:41.000Z",
    "fulfillmentModes": [
      "pickup",
      "delivery",
      "in-store"
    ],
    "id": "kroger-observation-53100516-0001111088318-2026-07-24",
    "itemSize": "4 lb",
    "limitation": "Dated internal research observation for one governed Mariano’s location; public live price comparison remains disabled.",
    "locationId": "kroger-location-53100516",
    "mappingId": "kroger-0001111088318",
    "observedAt": "2026-07-24T05:10:41Z",
    "priceAmount": 4.39,
    "priceType": "regular",
    "promotionalPrice": null,
    "providerInventoryState": "HIGH",
    "publicationState": "internal-only",
    "regularPrice": 4.39,
    "sourceId": "kroger"
  },
  {
    "availability": "available",
    "currency": "USD",
    "expiresAt": "2026-07-24T11:10:41.000Z",
    "fulfillmentModes": [
      "pickup",
      "delivery",
      "in-store"
    ],
    "id": "kroger-observation-53100516-0001111089875-2026-07-24",
    "itemSize": "32 oz",
    "limitation": "Dated internal research observation for one governed Mariano’s location; public live price comparison remains disabled.",
    "locationId": "kroger-location-53100516",
    "mappingId": "kroger-0001111089875",
    "observedAt": "2026-07-24T05:10:41Z",
    "priceAmount": 2.79,
    "priceType": "regular",
    "promotionalPrice": null,
    "providerInventoryState": "HIGH",
    "publicationState": "internal-only",
    "regularPrice": 2.79,
    "sourceId": "kroger"
  },
  {
    "availability": "available",
    "currency": "USD",
    "expiresAt": "2026-07-24T11:10:41.000Z",
    "fulfillmentModes": [
      "pickup",
      "delivery",
      "in-store"
    ],
    "id": "kroger-observation-53100516-0001111090765-2026-07-24",
    "itemSize": "8.1 oz",
    "limitation": "Dated internal research observation for one governed Mariano’s location; public live price comparison remains disabled.",
    "locationId": "kroger-location-53100516",
    "mappingId": "kroger-0001111090765",
    "observedAt": "2026-07-24T05:10:41Z",
    "priceAmount": 3.29,
    "priceType": "regular",
    "promotionalPrice": null,
    "providerInventoryState": "HIGH",
    "publicationState": "internal-only",
    "regularPrice": 3.29,
    "sourceId": "kroger"
  },
  {
    "availability": "unavailable",
    "currency": "USD",
    "expiresAt": "2026-07-24T11:10:41.000Z",
    "fulfillmentModes": [],
    "id": "kroger-observation-53100516-0001580003062-2026-07-24",
    "itemSize": "4 lb",
    "limitation": "Dated internal research observation for one governed Mariano’s location; public live price comparison remains disabled.",
    "locationId": "kroger-location-53100516",
    "mappingId": "kroger-0001580003062",
    "observedAt": "2026-07-24T05:10:41Z",
    "priceAmount": 5.99,
    "priceType": "regular",
    "promotionalPrice": null,
    "providerInventoryState": "TEMPORARILY_OUT_OF_STOCK",
    "publicationState": "internal-only",
    "regularPrice": 5.99,
    "sourceId": "kroger"
  },
  {
    "availability": "available",
    "currency": "USD",
    "expiresAt": "2026-07-24T11:10:41.000Z",
    "fulfillmentModes": [
      "pickup",
      "delivery",
      "in-store"
    ],
    "id": "kroger-observation-53100516-0001600010610-2026-07-24",
    "itemSize": "5 lbs",
    "limitation": "Dated internal research observation for one governed Mariano’s location; public live price comparison remains disabled.",
    "locationId": "kroger-location-53100516",
    "mappingId": "kroger-0001600010610",
    "observedAt": "2026-07-24T05:10:41Z",
    "priceAmount": 6.29,
    "priceType": "regular",
    "promotionalPrice": null,
    "providerInventoryState": "HIGH",
    "publicationState": "internal-only",
    "regularPrice": 6.29,
    "sourceId": "kroger"
  },
  {
    "availability": "unavailable",
    "currency": "USD",
    "expiresAt": "2026-07-24T11:10:41.000Z",
    "fulfillmentModes": [
      "pickup",
      "delivery",
      "in-store"
    ],
    "id": "kroger-observation-53100516-0001990000320-2026-07-24",
    "itemSize": "8.1 oz",
    "limitation": "Dated internal research observation for one governed Mariano’s location; public live price comparison remains disabled.",
    "locationId": "kroger-location-53100516",
    "mappingId": "kroger-0001990000320",
    "observedAt": "2026-07-24T05:10:41Z",
    "priceAmount": 3.79,
    "priceType": "regular",
    "promotionalPrice": null,
    "providerInventoryState": "TEMPORARILY_OUT_OF_STOCK",
    "publicationState": "internal-only",
    "regularPrice": 3.79,
    "sourceId": "kroger"
  },
  {
    "availability": "available",
    "currency": "USD",
    "expiresAt": "2026-07-24T11:10:41.000Z",
    "fulfillmentModes": [
      "pickup",
      "delivery",
      "in-store"
    ],
    "id": "kroger-observation-53100516-0002460001003-2026-07-24",
    "itemSize": "26 oz",
    "limitation": "Dated internal research observation for one governed Mariano’s location; public live price comparison remains disabled.",
    "locationId": "kroger-location-53100516",
    "mappingId": "kroger-0002460001003",
    "observedAt": "2026-07-24T05:10:41Z",
    "priceAmount": 2.29,
    "priceType": "regular",
    "promotionalPrice": null,
    "providerInventoryState": "HIGH",
    "publicationState": "internal-only",
    "regularPrice": 2.29,
    "sourceId": "kroger"
  },
  {
    "availability": "available",
    "currency": "USD",
    "expiresAt": "2026-07-24T11:10:41.000Z",
    "fulfillmentModes": [
      "pickup",
      "delivery",
      "in-store"
    ],
    "id": "kroger-observation-53100516-0002460001093-2026-07-24",
    "itemSize": "17.6 oz",
    "limitation": "Dated internal research observation for one governed Mariano’s location; public live price comparison remains disabled.",
    "locationId": "kroger-location-53100516",
    "mappingId": "kroger-0002460001093",
    "observedAt": "2026-07-24T05:10:41Z",
    "priceAmount": 3.99,
    "priceType": "regular",
    "promotionalPrice": null,
    "providerInventoryState": "HIGH",
    "publicationState": "internal-only",
    "regularPrice": 3.99,
    "sourceId": "kroger"
  },
  {
    "availability": "available",
    "currency": "USD",
    "expiresAt": "2026-07-24T11:10:41.000Z",
    "fulfillmentModes": [
      "pickup",
      "delivery",
      "in-store"
    ],
    "id": "kroger-observation-53100516-0003320001110-2026-07-24",
    "itemSize": "1 lb",
    "limitation": "Dated internal research observation for one governed Mariano’s location; public live price comparison remains disabled.",
    "locationId": "kroger-location-53100516",
    "mappingId": "kroger-0003320001110",
    "observedAt": "2026-07-24T05:10:41Z",
    "priceAmount": 1.49,
    "priceType": "regular",
    "promotionalPrice": null,
    "providerInventoryState": "HIGH",
    "publicationState": "internal-only",
    "regularPrice": 1.49,
    "sourceId": "kroger"
  },
  {
    "availability": "available",
    "currency": "USD",
    "expiresAt": "2026-07-24T11:10:41.000Z",
    "fulfillmentModes": [
      "pickup",
      "delivery",
      "in-store"
    ],
    "id": "kroger-observation-53100516-0003320001140-2026-07-24",
    "itemSize": "2 lb",
    "limitation": "Dated internal research observation for one governed Mariano’s location; public live price comparison remains disabled.",
    "locationId": "kroger-location-53100516",
    "mappingId": "kroger-0003320001140",
    "observedAt": "2026-07-24T05:10:41Z",
    "priceAmount": 2.49,
    "priceType": "regular",
    "promotionalPrice": null,
    "providerInventoryState": "HIGH",
    "publicationState": "internal-only",
    "regularPrice": 2.49,
    "sourceId": "kroger"
  },
  {
    "availability": "unknown",
    "currency": "USD",
    "expiresAt": "2026-07-24T11:10:41.000Z",
    "fulfillmentModes": [
      "pickup",
      "delivery",
      "in-store"
    ],
    "id": "kroger-observation-53100516-0003997803391-2026-07-24",
    "itemSize": "16 oz",
    "limitation": "Dated internal research observation for one governed Mariano’s location; public live price comparison remains disabled.",
    "locationId": "kroger-location-53100516",
    "mappingId": "kroger-0003997803391",
    "observedAt": "2026-07-24T05:10:41Z",
    "priceAmount": 3.99,
    "priceType": "regular",
    "promotionalPrice": null,
    "providerInventoryState": null,
    "publicationState": "internal-only",
    "regularPrice": 3.99,
    "sourceId": "kroger"
  },
  {
    "availability": "unknown",
    "currency": "USD",
    "expiresAt": "2026-07-24T11:10:41.000Z",
    "fulfillmentModes": [
      "pickup",
      "delivery",
      "in-store"
    ],
    "id": "kroger-observation-53100516-0003997803392-2026-07-24",
    "itemSize": "14 oz",
    "limitation": "Dated internal research observation for one governed Mariano’s location; public live price comparison remains disabled.",
    "locationId": "kroger-location-53100516",
    "mappingId": "kroger-0003997803392",
    "observedAt": "2026-07-24T05:10:41Z",
    "priceAmount": 5.79,
    "priceType": "regular",
    "promotionalPrice": null,
    "providerInventoryState": null,
    "publicationState": "internal-only",
    "regularPrice": 5.79,
    "sourceId": "kroger"
  },
  {
    "availability": "unknown",
    "currency": "USD",
    "expiresAt": "2026-07-24T11:10:41.000Z",
    "fulfillmentModes": [
      "pickup",
      "delivery",
      "in-store"
    ],
    "id": "kroger-observation-53100516-0003997853301-2026-07-24",
    "itemSize": "5 lb",
    "limitation": "Dated internal research observation for one governed Mariano’s location; public live price comparison remains disabled.",
    "locationId": "kroger-location-53100516",
    "mappingId": "kroger-0003997853301",
    "observedAt": "2026-07-24T05:10:41Z",
    "priceAmount": 6.99,
    "priceType": "regular",
    "promotionalPrice": null,
    "providerInventoryState": null,
    "publicationState": "internal-only",
    "regularPrice": 6.99,
    "sourceId": "kroger"
  },
  {
    "availability": "available",
    "currency": "USD",
    "expiresAt": "2026-07-24T11:10:41.000Z",
    "fulfillmentModes": [
      "pickup",
      "delivery",
      "in-store"
    ],
    "id": "kroger-observation-53100516-0004920004550-2026-07-24",
    "itemSize": "4 lb",
    "limitation": "Dated internal research observation for one governed Mariano’s location; public live price comparison remains disabled.",
    "locationId": "kroger-location-53100516",
    "mappingId": "kroger-0004920004550",
    "observedAt": "2026-07-24T05:10:41Z",
    "priceAmount": 5.99,
    "priceType": "regular",
    "promotionalPrice": null,
    "providerInventoryState": "HIGH",
    "publicationState": "internal-only",
    "regularPrice": 5.99,
    "sourceId": "kroger"
  },
  {
    "availability": "available",
    "currency": "USD",
    "expiresAt": "2026-07-24T11:10:41.000Z",
    "fulfillmentModes": [
      "pickup",
      "delivery",
      "in-store"
    ],
    "id": "kroger-observation-53100516-0005210074602-2026-07-24",
    "itemSize": "2.12 oz",
    "limitation": "Dated internal research observation for one governed Mariano’s location; public live price comparison remains disabled.",
    "locationId": "kroger-location-53100516",
    "mappingId": "kroger-0005210074602",
    "observedAt": "2026-07-24T05:10:41Z",
    "priceAmount": 3.79,
    "priceType": "regular",
    "promotionalPrice": null,
    "providerInventoryState": "HIGH",
    "publicationState": "internal-only",
    "regularPrice": 3.79,
    "sourceId": "kroger"
  },
  {
    "availability": "available",
    "currency": "USD",
    "expiresAt": "2026-07-24T11:10:41.000Z",
    "fulfillmentModes": [
      "pickup",
      "delivery",
      "in-store"
    ],
    "id": "kroger-observation-53100516-0007101201050-2026-07-24",
    "itemSize": "5 lbs",
    "limitation": "Dated internal research observation for one governed Mariano’s location; public live price comparison remains disabled.",
    "locationId": "kroger-location-53100516",
    "mappingId": "kroger-0007101201050",
    "observedAt": "2026-07-24T05:10:41Z",
    "priceAmount": 7.49,
    "priceType": "regular",
    "promotionalPrice": null,
    "providerInventoryState": "HIGH",
    "publicationState": "internal-only",
    "regularPrice": 7.49,
    "sourceId": "kroger"
  },
  {
    "availability": "available",
    "currency": "USD",
    "expiresAt": "2026-07-24T11:10:41.000Z",
    "fulfillmentModes": [
      "pickup",
      "delivery",
      "in-store"
    ],
    "id": "kroger-observation-53100516-0071514150349-2026-07-24",
    "itemSize": "1 dozen",
    "limitation": "Dated internal research observation for one governed Mariano’s location; public live price comparison remains disabled.",
    "locationId": "kroger-location-53100516",
    "mappingId": "kroger-0071514150349",
    "observedAt": "2026-07-24T05:10:41Z",
    "priceAmount": 5.99,
    "priceType": "regular",
    "promotionalPrice": null,
    "providerInventoryState": "HIGH",
    "publicationState": "internal-only",
    "regularPrice": 5.99,
    "sourceId": "kroger"
  },
  {
    "availability": "unknown",
    "currency": "USD",
    "expiresAt": "2026-07-24T11:10:41.000Z",
    "fulfillmentModes": [
      "pickup",
      "delivery",
      "in-store"
    ],
    "id": "kroger-observation-53100516-0004900002890-2026-07-24",
    "itemSize": "12 pk / 12 fl oz",
    "limitation": "Dated internal research observation for one governed Mariano’s location; public live price comparison remains disabled.",
    "locationId": "kroger-location-53100516",
    "mappingId": "kroger-coca-cola-alias",
    "observedAt": "2026-07-24T05:10:41Z",
    "priceAmount": 11.99,
    "priceType": "regular",
    "promotionalPrice": null,
    "providerInventoryState": null,
    "publicationState": "internal-only",
    "regularPrice": 11.99,
    "sourceId": "kroger"
  },
  {
    "availability": "available",
    "currency": "USD",
    "expiresAt": "2026-07-24T11:10:41.000Z",
    "fulfillmentModes": [
      "pickup",
      "delivery",
      "in-store"
    ],
    "id": "kroger-observation-53100516-0002100065883-2026-07-24",
    "itemSize": "7.25 oz",
    "limitation": "Dated internal research observation for one governed Mariano’s location; public live price comparison remains disabled.",
    "locationId": "kroger-location-53100516",
    "mappingId": "kroger-kraft-mac-cheese",
    "observedAt": "2026-07-24T05:10:41Z",
    "priceAmount": 1.25,
    "priceType": "promotional",
    "promotionalPrice": 1.25,
    "providerInventoryState": "HIGH",
    "publicationState": "internal-only",
    "regularPrice": 1.39,
    "sourceId": "kroger"
  }
]
